{
	"translations": {
		"de": {
			"Metervalue which should be used": "Zählerwert welcher ausgelesen werden soll.",
			"Metervariable": "Zählervariable",
			"Leak timer interval": "Kleinverbrauch Zeitintervall",
			"Burst timer interval": "Großverbrauch Zeitintervall",
			"Minutes": "Minuten",
			"No activity": "Keine Aktivität",
			"Everything fine": "Alles im grünen Bereich",
			"Normal activity": "Normale Aktivität",
			"High activity": "Erhöhte Aktivität",
			"Abnormal activity": "Unnormale Aktivität",
			"Pre-Alarm": "Vor-Alarm",
			"Alarm triggered": "Alarm ausgelöst",
			"Leak": "Kleinverbrauch",
			"Leak threshold": "Kleinverbrauch Grenzwert",
			"Burst": "Großverbrauch",
			"Burst threshold": "Großverbrauch Grenzwert",
			"Invalid Ident": "Unzulässiger Ident",
			"Type of Flow": "Durchflussart",
			"Water": "Wasser",
			"Electricity": "Strom",
			"Gas":"Gas",
			"Alarm Alert": "Alarmbenachichtigung",
			"Alert threshold": "Alarmauslöser",
			"Timer interval": "Zeitintervall"
		}
	}
}